SyncLink/SyncLink.py
SyncLink/__init__.py
synclink-0.1.3.dist-info/METADATA
synclink-0.1.3.dist-info/WHEEL
synclink-0.1.3.dist-info/top_level.txt
synclink-0.1.3.dist-info/RECORD
