Metadata-Version: 2.4
Name: SyncLink
Version: 0.1.3
Summary: A Modern way to sync files
Author: Tristan McBride Sr.
Author-email: "Tristan McBride Sr." <142635792+TristanMcBrideSr@users.noreply.github.com>
Maintainer-email: "Tristan McBride Sr." <142635792+TristanMcBrideSr@users.noreply.github.com>
License-Expression: Apache-2.0
Project-URL: Homepage, https://github.com/TristanMcBrideSr
Keywords: AI,Agents,Skills,Productivity,Automation,Voice Assistant,Chatbot,LLM,Large Language Model
Classifier: Programming Language :: Python :: 3
Classifier: Operating System :: OS Independent
Classifier: Intended Audience :: Developers
Requires-Python: >=3.10
Requires-Dist: requests
Dynamic: author
